blockbax_sdk/__init__.py
blockbax_sdk/client/__init__.py
blockbax_sdk/client/api/__init__.py
blockbax_sdk/client/api/api.py
blockbax_sdk/client/api/api_utils.py
blockbax_sdk/client/api/readme.md
blockbax_sdk/client/http_client.py
blockbax_sdk/errors.py
blockbax_sdk/models/__init__.py
blockbax_sdk/models/base.py
blockbax_sdk/models/data_types.py
blockbax_sdk/models/event.py
blockbax_sdk/models/event_trigger.py
blockbax_sdk/models/ingestion.py
blockbax_sdk/models/measurement.py
blockbax_sdk/models/metric.py
blockbax_sdk/models/project.py
blockbax_sdk/models/property_type.py
blockbax_sdk/models/property_type_value.py
blockbax_sdk/models/series.py
blockbax_sdk/models/subject.py
blockbax_sdk/models/subject_property.py
blockbax_sdk/models/subject_type.py
blockbax_sdk/models/type_hints.py
blockbax_sdk/models/utils.py
blockbax_sdk/py.typed
blockbax_sdk/util/__init__.py
blockbax_sdk/util/conversions.py
blockbax_sdk/util/deprecated.py
blockbax_sdk/util/ingestion_queuer.py
blockbax_sdk-1.5.0.dist-info/METADATA
blockbax_sdk-1.5.0.dist-info/WHEEL
blockbax_sdk-1.5.0.dist-info/licenses/LICENSE
blockbax_sdk-1.5.0.dist-info/RECORD
